{"url":"https:\/\/crm.springfieldproperties.ae\/rest\/8\/11bxi7ddg3ykpqkz\/user.current.json","info":{"url":"https:\/\/crm.springfieldproperties.ae\/rest\/8\/11bxi7ddg3ykpqkz\/user.current.json","content_type":"application\/json; charset=utf-8","http_code":200,"header_size":1087,"request_size":145,"filetime":-1,"ssl_verify_result":0,"redirect_count":0,"total_time":0.89389799999999997037747334616142325103282928466796875,"namelookup_time":0.033298000000000001208366740002020378597080707550048828125,"connect_time":0.295182000000000055450755098718218505382537841796875,"pretransfer_time":0.58939500000000000223820961764431558549404144287109375,"size_upload":0,"size_download":929,"speed_download":1039,"speed_upload":0,"download_content_length":-1,"upload_content_length":-1,"starttransfer_time":0.89387099999999997113064864606712944805622100830078125,"redirect_time":0,"redirect_url":"","primary_ip":"54.83.26.42","certinfo":[],"primary_port":443,"local_ip":"192.168.1.77","local_port":34114,"http_version":2,"protocol":2,"ssl_verifyresult":0,"scheme":"HTTPS"},"params":{"method":"user.current","params":[]},"result":{"result":{"ID":"8","XML_ID":"52575623","ACTIVE":true,"NAME":"Vortexweb","LAST_NAME":"","EMAIL":"vortexwebcloud@gmail.com","LAST_LOGIN":"2024-10-26T12:21:02+03:00","DATE_REGISTER":"2024-09-11T03:00:00+03:00","IS_ONLINE":"Y","TIME_ZONE_OFFSET":"9000","TIMESTAMP_X":"10\/26\/2024 09:22:07 am","LAST_ACTIVITY_DATE":"2024-10-26 13:06:51","PERSONAL_GENDER":"","PERSONAL_BIRTHDAY":"","PERSONAL_PHOTO":"https:\/\/cdn.bitrix24.com\/b30933017\/main\/44c\/44cb70c10128501f78718521b7bb8c98\/Screenshot 2024-09-12 at 11.14.21_PM.png","UF_EMPLOYMENT_DATE":"","UF_DEPARTMENT":[1],"UF_USR_1727158528318":"","UF_USR_1727162511923":"","UF_USR_1727162521074":"","UF_USR_1727162526938":""},"time":{"start":1729937420.966084957122802734375,"finish":1729937420.98581600189208984375,"duration":0.019731044769287109375,"processing":0.001655101776123046875,"date_start":"2024-10-26T13:10:20+03:00","date_finish":"2024-10-26T13:10:20+03:00","operating_reset_at":1729938020,"operating":0}}}